vidstream/__init__.py
vidstream/streaming.py
dcordts-0.0.13.dist-info/LICENSE
dcordts-0.0.13.dist-info/METADATA
dcordts-0.0.13.dist-info/WHEEL
dcordts-0.0.13.dist-info/top_level.txt
dcordts-0.0.13.dist-info/RECORD
